cli.py
src/__init__.py
src/commands/__init__.py
src/commands/performance/__init__.py
src/commands/performance/lighthouse.py
src/commands/performance/metrics.py
src/performance/__init__.py
src/performance/lighthouse_report.py
src/performance/lighthouse_report_factory.py
src/performance/performance_metrics.py
src/performance/performance_metrics_factory.py
src/utils/__init__.py
src/utils/command.py
src/utils/config.py
src/utils/csv_writer.py
src/utils/file.py
src/utils/time.py
src/utils/validator.py
ttb_cli-1.7.dist-info/LICENSE
ttb_cli-1.7.dist-info/METADATA
ttb_cli-1.7.dist-info/WHEEL
ttb_cli-1.7.dist-info/entry_points.txt
ttb_cli-1.7.dist-info/top_level.txt
ttb_cli-1.7.dist-info/RECORD
