Metadata-Version: 2.1
Name: ttb-cli
Version: 1.7
Requires-Python: ~=3.10
License-File: LICENSE
Requires-Dist: Requests~=2.32.3
Requires-Dist: pyppeteer~=2.0.0
Requires-Dist: click~=8.1.7
Requires-Dist: PyYAML~=6.0.2
Requires-Dist: tqdm~=4.66.5
